odoo9_addon_product_sequence-9.0.1.0.0-py2.7-nspkg.pth
odoo_addons/product_sequence/__openerp__.py
odoo_addons/product_sequence/hooks.py
odoo_addons/product_sequence/__init__.py
odoo_addons/product_sequence/README.rst
odoo_addons/product_sequence/models/product_product.py
odoo_addons/product_sequence/models/__init__.py
odoo_addons/product_sequence/i18n/product_sequence.pot
odoo_addons/product_sequence/i18n/es.po
odoo_addons/product_sequence/i18n/ca.po
odoo_addons/product_sequence/i18n/de.po
odoo_addons/product_sequence/data/product_sequence.xml
odoo_addons/product_sequence/tests/__init__.py
odoo_addons/product_sequence/tests/test_product_sequence.py
odoo_addons/product_sequence/demo/product_product.xml
odoo_addons/product_sequence/static/description/icon.png
odoo9_addon_product_sequence-9.0.1.0.0.dist-info/top_level.txt
odoo9_addon_product_sequence-9.0.1.0.0.dist-info/WHEEL
odoo9_addon_product_sequence-9.0.1.0.0.dist-info/RECORD
odoo9_addon_product_sequence-9.0.1.0.0.dist-info/metadata.json
odoo9_addon_product_sequence-9.0.1.0.0.dist-info/DESCRIPTION.rst
odoo9_addon_product_sequence-9.0.1.0.0.dist-info/METADATA
odoo9_addon_product_sequence-9.0.1.0.0.dist-info/namespace_packages.txt
